kuryr_libnetwork/__init__.py
kuryr_libnetwork/config.py
kuryr_libnetwork/constants.py
kuryr_libnetwork/controllers.py
kuryr_libnetwork/opts.py
kuryr_libnetwork/server.py
kuryr_libnetwork/utils.py
kuryr_libnetwork/version.py
kuryr_libnetwork/port_driver/__init__.py
kuryr_libnetwork/port_driver/base.py
kuryr_libnetwork/port_driver/driver.py
kuryr_libnetwork/port_driver/drivers/__init__.py
kuryr_libnetwork/port_driver/drivers/nested.py
kuryr_libnetwork/port_driver/drivers/sriov.py
kuryr_libnetwork/port_driver/drivers/veth.py
kuryr_libnetwork/port_driver/drivers/vlan.py
kuryr_libnetwork/schemata/__init__.py
kuryr_libnetwork/schemata/commons.py
kuryr_libnetwork/schemata/endpoint_create.py
kuryr_libnetwork/schemata/endpoint_delete.py
kuryr_libnetwork/schemata/endpoint_info.py
kuryr_libnetwork/schemata/join.py
kuryr_libnetwork/schemata/leave.py
kuryr_libnetwork/schemata/network_create.py
kuryr_libnetwork/schemata/network_delete.py
kuryr_libnetwork/schemata/release_address.py
kuryr_libnetwork/schemata/release_pool.py
kuryr_libnetwork/schemata/request_address.py
kuryr_libnetwork/schemata/request_pool.py
kuryr_libnetwork/tests/__init__.py
kuryr_libnetwork/tests/contrib/gate_hook.sh
kuryr_libnetwork/tests/contrib/post_test_hook.sh
kuryr_libnetwork/tests/fullstack/__init__.py
kuryr_libnetwork/tests/fullstack/kuryr_base.py
kuryr_libnetwork/tests/fullstack/test_container.py
kuryr_libnetwork/tests/fullstack/test_ipam.py
kuryr_libnetwork/tests/fullstack/test_network.py
kuryr_libnetwork/tests/unit/__init__.py
kuryr_libnetwork/tests/unit/base.py
kuryr_libnetwork/tests/unit/test_config.py
kuryr_libnetwork/tests/unit/test_external_connectivity.py
kuryr_libnetwork/tests/unit/test_ipam_pool.py
kuryr_libnetwork/tests/unit/test_join.py
kuryr_libnetwork/tests/unit/test_kuryr.py
kuryr_libnetwork/tests/unit/test_kuryr_endpoint.py
kuryr_libnetwork/tests/unit/test_kuryr_existing_network.py
kuryr_libnetwork/tests/unit/test_kuryr_ipam.py
kuryr_libnetwork/tests/unit/test_kuryr_network.py
kuryr_libnetwork-16.0.0.dist-info/AUTHORS
kuryr_libnetwork-16.0.0.dist-info/LICENSE
kuryr_libnetwork-16.0.0.dist-info/METADATA
kuryr_libnetwork-16.0.0.dist-info/WHEEL
kuryr_libnetwork-16.0.0.dist-info/entry_points.txt
kuryr_libnetwork-16.0.0.dist-info/pbr.json
kuryr_libnetwork-16.0.0.dist-info/top_level.txt
kuryr_libnetwork-16.0.0.dist-info/RECORD
