Metadata-Version: 2.1
Name: kuryr-libnetwork
Version: 16.0.0
Summary: Docker libnetwork driver for OpenStack Neutron
Home-page: https://docs.openstack.org/kuryr-libnetwork/latest/
Author: OpenStack
Author-email: openstack-discuss@lists.openstack.org
Classifier: Environment :: OpenStack
Classifier: Intended Audience :: Information Technology
Classifier: Intended Audience :: System Administrators
Classifier: License :: OSI Approved :: Apache Software License
Classifier: Operating System :: POSIX :: Linux
Classifier: Programming Language :: Python
Classifier: Programming Language :: Python :: Implementation :: CPython
Classifier: Programming Language :: Python :: 3 :: Only
Classifier: Programming Language :: Python :: 3
Classifier: Programming Language :: Python :: 3.8
Classifier: Programming Language :: Python :: 3.9
Classifier: Programming Language :: Python :: 3.10
Classifier: Programming Language :: Python :: 3.11
Requires-Python: >=3.8
License-File: LICENSE
License-File: AUTHORS
Requires-Dist: Babel !=2.4.0,>=2.3.4
Requires-Dist: Flask !=0.11,>=0.10
Requires-Dist: jsonschema >=3.2.0
Requires-Dist: kuryr-lib >=0.7.0
Requires-Dist: neutron-lib >=1.13.0
Requires-Dist: os-client-config >=1.28.0
Requires-Dist: oslo.concurrency >=3.25.0
Requires-Dist: oslo.config >=5.2.0
Requires-Dist: oslo.log >=3.36.0
Requires-Dist: oslo.utils >=3.33.0
Requires-Dist: pbr !=2.1.0,>=2.0.0
Requires-Dist: python-neutronclient >=6.7.0
